LICENSE
MANIFEST.in
README.rst
setup.cfg
setup.py
versioneer.py
artellapipe/__init__.py
artellapipe/libs/__init__.py
artellapipe/libs/alembic/__init__.py
artellapipe/libs/alembic/__logging__.ini
artellapipe/libs/alembic/__version__.py
artellapipe/libs/alembic/_version.py
artellapipe/libs/alembic/core/__init__.py
artellapipe/libs/alembic/core/alembic.py
artellapipe/libs/alembic/houdini/__init__.py
artellapipe/libs/alembic/houdini/alembic.py
artellapipe/libs/alembic/maya/__init__.py
artellapipe/libs/alembic/maya/alembic.py
artellapipe_libs_alembic.egg-info/PKG-INFO
artellapipe_libs_alembic.egg-info/SOURCES.txt
artellapipe_libs_alembic.egg-info/dependency_links.txt
artellapipe_libs_alembic.egg-info/not-zip-safe
artellapipe_libs_alembic.egg-info/requires.txt
artellapipe_libs_alembic.egg-info/top_level.txt
tests/__init__.py
tests/test_general.py