Metadata-Version: 2.1
Name: artellapipe-libs-alembic
Version: 0.0.5
Summary: Library to handle Alembics
Home-page: https://github.com/ArtellaPipe/artellapipe-libs-alembic
Author: Tomas Poveda
Author-email: tpovedatd@gmail.com
License: MIT
Platform: UNKNOWN
Provides-Extra: dev
Provides-Extra: test
